webargparse/__init__.py
webargparse/__main__.py
webargparse/homepage.py
webargparse/types.py
webargparse/example/__init__.py
webargparse/example/demo.py
webargparse/example/demo1.py
webargparse/example/demo2.py
webargparse/pages/__init__.py
webargparse/pages/argparsepage.py
pywebargparse-0.1.1.dist-info/LICENSE
pywebargparse-0.1.1.dist-info/METADATA
pywebargparse-0.1.1.dist-info/WHEEL
pywebargparse-0.1.1.dist-info/top_level.txt
pywebargparse-0.1.1.dist-info/RECORD
