Metadata-Version: 2.1
Name: pywebargparse
Version: 0.1.1
Summary: This is a tool to create an web ui from argparse script
Home-page: https://github.com/penfree/webargparse
Author: penfree
Author-email: UNKNOWN
License: UNKNOWN
Platform: UNKNOWN
Requires-Dist: streamlit
Requires-Dist: watchdog
Requires-Dist: streamlit-aggrid
